Metadata-Version: 2.1
Name: startup-flask-app
Version: 6.2.1
Summary: A small example package
Home-page: https://github.com/ArcadeDesigns
Author: ArcadeDesigns (Ebire Folayemi Michael)
Author-email: Ebire Folayemi <folayemiebire@gmail.com>
Project-URL: Homepage, https://github.com/ArcadeDesigns/startup_flask_app
Project-URL: Bug Tracker, https://github.com/ArcadeDesigns/startup_flask_app/issues
Keywords: python,Flask,Flask setup,web application,full-stack development
Classifier: Programming Language :: Python :: 3
Classifier: License :: OSI Approved :: BSD License
Classifier: Operating System :: OS Independent
Requires-Python: >=3.7
License-File: LICENSE
